subtotal_ai_toolkit/__init__.py
subtotal_ai_toolkit/api.py
subtotal_ai_toolkit/configuration.py
subtotal_ai_toolkit/functions.py
subtotal_ai_toolkit/prompts.py
subtotal_ai_toolkit/schema.py
subtotal_ai_toolkit/tools.py
subtotal_ai_toolkit/crewai/tool.py
subtotal_ai_toolkit/crewai/toolkit.py
subtotal_ai_toolkit/langchain/tool.py
subtotal_ai_toolkit/langchain/toolkit.py
subtotal_ai_toolkit/openai/toolkit.py
subtotal_ai_toolkit-0.2.0.dist-info/LICENSE
subtotal_ai_toolkit-0.2.0.dist-info/METADATA
subtotal_ai_toolkit-0.2.0.dist-info/WHEEL
subtotal_ai_toolkit-0.2.0.dist-info/top_level.txt
subtotal_ai_toolkit-0.2.0.dist-info/RECORD
