Metadata-Version: 2.2
Name: subtotal-ai-toolkit
Version: 0.2.0
Summary: Subtotal AI Toolkit
Author-email: Subtotal <support@subtotal.com>
License: The MIT License (MIT)
Project-URL: Bug Tracker, https://github.com/subtotal-inc/ai-toolkit/issues
Project-URL: Source Code, https://github.com/subtotal-inc/ai-toolkit
Keywords: subtotal,api
Requires-Python: >=3.11
License-File: LICENSE
Requires-Dist: pydantic<3.0.0,>=2.9.0
Provides-Extra: openai
Requires-Dist: openai<2.0.0,>=1.65.0; extra == "openai"
Provides-Extra: langchain
Requires-Dist: langchain<1.0.0,>=0.3.0; extra == "langchain"
Provides-Extra: crewai
Requires-Dist: crewai<1.0.0,>=0.76.0; extra == "crewai"
Requires-Dist: crewai-tools<1.0.0,>=0.13.0; extra == "crewai"
Provides-Extra: all
Requires-Dist: subtotal-ai-toolkit[crewai,langchain,openai]; extra == "all"
